MANIFEST.in
README.rst
setup.py
stock_extractor/__init__.py
stock_extractor.egg-info/PKG-INFO
stock_extractor.egg-info/SOURCES.txt
stock_extractor.egg-info/dependency_links.txt
stock_extractor.egg-info/not-zip-safe
stock_extractor.egg-info/requires.txt
stock_extractor.egg-info/top_level.txt