Metadata-Version: 1.1
Name: stock-extractor
Version: 0.1
Summary: a general purpose stock data extractor
Home-page: https://github.com/ZachLiuGIS/stock_extractor
Author: Zach Liu
Author-email: zachliugis@gmail.com
License: MIT
Keywords: stock,finance,market
Platform: UNKNOWN
Classifier: License :: OSI Approved :: MIT License
Classifier: Programming Language :: Python :: 3.4
Classifier: Topic :: Office/Business :: Financial
